pipr/__init__.py
pipr/package_metadata.json
pipr/pipr.py
pipr/testpipr.py
pipr/try.py
pipr-0.0.50.data/scripts/.README
pipr-0.0.50.data/scripts/pipr
pipr-0.0.50.dist-info/DESCRIPTION.rst
pipr-0.0.50.dist-info/METADATA
pipr-0.0.50.dist-info/RECORD
pipr-0.0.50.dist-info/WHEEL
pipr-0.0.50.dist-info/metadata.json
pipr-0.0.50.dist-info/top_level.txt
