Metadata-Version: 2.0
Name: pipr
Version: 0.0.50
Summary: Tool to pip install missing imports and more
Home-page: http://github.com/yahoo/pipr
Author: Sergey Lupersolsky, Yash Bathia
Author-email: ypython@yahoogroups.com
License: BSD
Platform: UNKNOWN
Classifier: License :: OSI Approved :: BSD License
Classifier: Operating System :: POSIX :: Linux
Classifier: Programming Language :: Python
Requires-Dist: six
